{
  "template": {
    "id": 3703,
    "templateName": "Vendor Creation Sample BUD",
    "key": "TMPTS03703",
    "companyCode": "ubgroup",
    "documentTypes": [
      {
        "id": 37030,
        "documentType": "Vendor Creation Sample BUD Process",
        "formFillMetadatas": [
          {
            "id": 37030001,
            "mandatory": false,
            "formTag": {
              "id": 370301,
              "name": "Basic Details",
              "type": "PANEL"
            }
          },
          {
            "id": 37030002,
            "mandatory": false,
            "formTag": {
              "id": 370302,
              "name": "Search term / Reference Number(Transaction ID)",
              "type": "TEXT"
            }
          },
          {
            "id": 37030003,
            "mandatory": false,
            "formTag": {
              "id": 370303,
              "name": "Created on",
              "type": "DATE"
            }
          },
          {
            "id": 37030004,
            "mandatory": false,
            "formTag": {
              "id": 370304,
              "name": "Created By",
              "type": "TEXT"
            }
          },
          {
            "id": 37030005,
            "mandatory": true,
            "formTag": {
              "id": 370305,
              "name": "Name/ First Name of the Organization",
              "type": "TEXT"
            }
          },
          {
            "id": 37030006,
            "mandatory": true,
            "formTag": {
              "id": 370306,
              "name": "Select the process type",
              "type": "DROPDOWN"
            }
          },
          {
            "id": 37030007,
            "mandatory": false,
            "formTag": {
              "id": 370307,
              "name": "Process Type",
              "type": "TEXT"
            }
          },
          {
            "id": 37030008,
            "mandatory": true,
            "formTag": {
              "id": 370308,
              "name": "Account Group/Vendor Type",
              "type": "DROPDOWN"
            }
          },
          {
            "id": 37030009,
            "mandatory": true,
            "formTag": {
              "id": 370309,
              "name": "Group key/Corporate Group",
              "type": "DROPDOWN"
            }
          },
          {
            "id": 37030010,
            "mandatory": true,
            "formTag": {
              "id": 370310,
              "name": "Vendor Domestic or Import",
              "type": "TEXT"
            }
          },
          {
            "id": 37030011,
            "mandatory": true,
            "formTag": {
              "id": 370311,
              "name": "Country",
              "type": "DROPDOWN"
            }
          },
          {
            "id": 37030012,
            "mandatory": false,
            "formTag": {
              "id": 370312,
              "name": "Country Name",
              "type": "TEXT"
            }
          },
          {
            "id": 37030013,
            "mandatory": false,
            "formTag": {
              "id": 370313,
              "name": "Country Code",
              "type": "TEXT"
            }
          },
          {
            "id": 37030014,
            "mandatory": true,
            "formTag": {
              "id": 370314,
              "name": "Company Code",
              "type": "DROPDOWN"
            }
          },
          {
            "id": 37030015,
            "mandatory": true,
            "formTag": {
              "id": 370315,
              "name": "Mobile Number",
              "type": "MOBILE"
            }
          },
          {
            "id": 37030016,
            "mandatory": false,
            "formTag": {
              "id": 370316,
              "name": "Do you wish to add additional mobile numbers (India)?",
              "type": "EXTERNAL_DROPDOWN"
            }
          },
          {
            "id": 37030017,
            "mandatory": false,
            "formTag": {
              "id": 370317,
              "name": "Do you wish to add additional mobile numbers (Non-India)?",
              "type": "EXTERNAL_DROPDOWN"
            }
          },
          {
            "id": 37030018,
            "mandatory": false,
            "formTag": {
              "id": 370318,
              "name": "Mobile Number 2 (Domestic)",
              "type": "TEXT"
            }
          },
          {
            "id": 37030019,
            "mandatory": false,
            "formTag": {
              "id": 370319,
              "name": "Mobile Number 3 (Domestic)",
              "type": "TEXT"
            }
          },
          {
            "id": 37030020,
            "mandatory": false,
            "formTag": {
              "id": 370320,
              "name": "Mobile Number 4 (Domestic)",
              "type": "TEXT"
            }
          },
          {
            "id": 37030021,
            "mandatory": false,
            "formTag": {
              "id": 370321,
              "name": "Mobile Number 5 (Domestic)",
              "type": "TEXT"
            }
          },
          {
            "id": 37030022,
            "mandatory": false,
            "formTag": {
              "id": 370322,
              "name": "Mobile Number 2 (Import)",
              "type": "TEXT"
            }
          },
          {
            "id": 37030023,
            "mandatory": false,
            "formTag": {
              "id": 370323,
              "name": "Mobile Number 3 (Import)",
              "type": "TEXT"
            }
          },
          {
            "id": 37030024,
            "mandatory": false,
            "formTag": {
              "id": 370324,
              "name": "Mobile Number 4 (Import)",
              "type": "TEXT"
            }
          },
          {
            "id": 37030025,
            "mandatory": false,
            "formTag": {
              "id": 370325,
              "name": "Mobile Number 5 (Import)",
              "type": "TEXT"
            }
          },
          {
            "id": 37030026,
            "mandatory": true,
            "formTag": {
              "id": 370326,
              "name": "Vendor Contact Email",
              "type": "TEXT"
            }
          },
          {
            "id": 37030027,
            "mandatory": true,
            "formTag": {
              "id": 370327,
              "name": "Vendor Contact Name",
              "type": "TEXT"
            }
          },
          {
            "id": 37030028,
            "mandatory": false,
            "formTag": {
              "id": 370328,
              "name": "Do you wish to add additional email addresses?",
              "type": "EXTERNAL_DROPDOWN"
            }
          },
          {
            "id": 37030029,
            "mandatory": false,
            "formTag": {
              "id": 370329,
              "name": "Email 2",
              "type": "TEXT"
            }
          },
          {
            "id": 37030030,
            "mandatory": false,
            "formTag": {
              "id": 370330,
              "name": "Concerned email addresses?",
              "type": "EXTERNAL_DROPDOWN"
            }
          },
          {
            "id": 37030031,
            "mandatory": false,
            "formTag": {
              "id": 370331,
              "name": "Email ID",
              "type": "TEXT"
            }
          },
          {
            "id": 37030032,
            "mandatory": false,
            "formTag": {
              "id": 370332,
              "name": "PAN and GST Details",
              "type": "PANEL"
            }
          },
          {
            "id": 37030033,
            "mandatory": false,
            "formTag": {
              "id": 370333,
              "name": "PAN DETAILS",
              "type": "LABEL"
            }
          },
          {
            "id": 37030034,
            "mandatory": false,
            "formTag": {
              "id": 370334,
              "name": "Upload PAN",
              "type": "FILE"
            }
          },
          {
            "id": 37030035,
            "mandatory": false,
            "formTag": {
              "id": 370335,
              "name": "PAN",
              "type": "TEXT"
            }
          },
          {
            "id": 37030036,
            "mandatory": false,
            "formTag": {
              "id": 370336,
              "name": "Pan Holder Name",
              "type": "TEXT"
            }
          },
          {
            "id": 37030037,
            "mandatory": false,
            "formTag": {
              "id": 370337,
              "name": "PAN Type",
              "type": "TEXT"
            }
          },
          {
            "id": 37030038,
            "mandatory": false,
            "formTag": {
              "id": 370338,
              "name": "PAN Status",
              "type": "TEXT"
            }
          },
          {
            "id": 37030039,
            "mandatory": false,
            "formTag": {
              "id": 370339,
              "name": "Aadhaar PAN List Status",
              "type": "TEXT"
            }
          },
          {
            "id": 37030040,
            "mandatory": false,
            "formTag": {
              "id": 370340,
              "name": "GST Details",
              "type": "LABEL"
            }
          },
          {
            "id": 37030041,
            "mandatory": false,
            "formTag": {
              "id": 370341,
              "name": "Please select GST option",
              "type": "EXTERNAL_DROPDOWN"
            }
          },
          {
            "id": 37030042,
            "mandatory": false,
            "formTag": {
              "id": 370342,
              "name": "GSTIN IMAGE",
              "type": "FILE"
            }
          },
          {
            "id": 37030043,
            "mandatory": false,
            "formTag": {
              "id": 370343,
              "name": "GSTIN",
              "type": "TEXT"
            }
          },
          {
            "id": 37030044,
            "mandatory": false,
            "formTag": {
              "id": 370344,
              "name": "Trade Name",
              "type": "TEXT"
            }
          },
          {
            "id": 37030045,
            "mandatory": false,
            "formTag": {
              "id": 370345,
              "name": "Legal Name",
              "type": "TEXT"
            }
          },
          {
            "id": 37030046,
            "mandatory": false,
            "formTag": {
              "id": 370346,
              "name": "Reg Date",
              "type": "TEXT"
            }
          },
          {
            "id": 37030047,
            "mandatory": false,
            "formTag": {
              "id": 370347,
              "name": "Type",
              "type": "TEXT"
            }
          },
          {
            "id": 37030048,
            "mandatory": false,
            "formTag": {
              "id": 370348,
              "name": "Building Number",
              "type": "TEXT"
            }
          },
          {
            "id": 37030049,
            "mandatory": false,
            "formTag": {
              "id": 370349,
              "name": "Street",
              "type": "TEXT"
            }
          },
          {
            "id": 37030050,
            "mandatory": false,
            "formTag": {
              "id": 370350,
              "name": "City",
              "type": "TEXT"
            }
          },
          {
            "id": 37030051,
            "mandatory": false,
            "formTag": {
              "id": 370351,
              "name": "District",
              "type": "TEXT"
            }
          },
          {
            "id": 37030052,
            "mandatory": false,
            "formTag": {
              "id": 370352,
              "name": "State",
              "type": "TEXT"
            }
          },
          {
            "id": 37030053,
            "mandatory": false,
            "formTag": {
              "id": 370353,
              "name": "Pin Code",
              "type": "TEXT"
            }
          },
          {
            "id": 37030054,
            "mandatory": false,
            "formTag": {
              "id": 370354,
              "name": "Upload Declaration",
              "type": "FILE"
            }
          },
          {
            "id": 37030055,
            "mandatory": false,
            "formTag": {
              "id": 370355,
              "name": "GST Vendor Classification",
              "type": "TEXT"
            }
          },
          {
            "id": 37030056,
            "mandatory": false,
            "formTag": {
              "id": 370356,
              "name": "ID Type",
              "type": "TEXT"
            }
          },
          {
            "id": 37030057,
            "mandatory": false,
            "formTag": {
              "id": 370357,
              "name": "Service Tax Registration Number",
              "type": "TEXT"
            }
          },
          {
            "id": 37030058,
            "mandatory": false,
            "formTag": {
              "id": 370358,
              "name": "Language Key",
              "type": "TEXT"
            }
          },
          {
            "id": 37030059,
            "mandatory": false,
            "formTag": {
              "id": 370359,
              "name": "Vendor Basic Details",
              "type": "PANEL"
            }
          },
          {
            "id": 37030060,
            "mandatory": false,
            "formTag": {
              "id": 370360,
              "name": "Name/ First Name of the Organization",
              "type": "TEXT"
            }
          },
          {
            "id": 37030061,
            "mandatory": false,
            "formTag": {
              "id": 370361,
              "name": "Name/ Middle Name of the Organization",
              "type": "TEXT"
            }
          },
          {
            "id": 37030062,
            "mandatory": false,
            "formTag": {
              "id": 370362,
              "name": "Name/ Last Name of the Organization",
              "type": "TEXT"
            }
          },
          {
            "id": 37030063,
            "mandatory": false,
            "formTag": {
              "id": 370363,
              "name": "Name 4/Alternate Name",
              "type": "TEXT"
            }
          },
          {
            "id": 37030064,
            "mandatory": false,
            "formTag": {
              "id": 370364,
              "name": "Title",
              "type": "EXTERNAL_DROPDOWN"
            }
          },
          {
            "id": 37030065,
            "mandatory": false,
            "formTag": {
              "id": 370365,
              "name": "Business Registration Number Available?",
              "type": "EXTERNAL_DROPDOWN"
            }
          },
          {
            "id": 37030066,
            "mandatory": false,
            "formTag": {
              "id": 370366,
              "name": "Business Registration Number",
              "type": "TEXT"
            }
          },
          {
            "id": 37030067,
            "mandatory": false,
            "formTag": {
              "id": 370367,
              "name": "Address Details",
              "type": "PANEL"
            }
          },
          {
            "id": 37030068,
            "mandatory": false,
            "formTag": {
              "id": 370368,
              "name": "Please Choose Address Proof",
              "type": "EXTERNAL_DROPDOWN"
            }
          },
          {
            "id": 37030069,
            "mandatory": false,
            "formTag": {
              "id": 370369,
              "name": "Electricity bill copy",
              "type": "FILE"
            }
          },
          {
            "id": 37030070,
            "mandatory": false,
            "formTag": {
              "id": 370370,
              "name": "Aadhaar Front copy",
              "type": "FILE"
            }
          },
          {
            "id": 37030071,
            "mandatory": false,
            "formTag": {
              "id": 370371,
              "name": "Aadhaar Back Image",
              "type": "FILE"
            }
          },
          {
            "id": 37030072,
            "mandatory": false,
            "formTag": {
              "id": 370372,
              "name": "Street",
              "type": "TEXT"
            }
          },
          {
            "id": 37030073,
            "mandatory": false,
            "formTag": {
              "id": 370373,
              "name": "Street 1",
              "type": "TEXT"
            }
          },
          {
            "id": 37030074,
            "mandatory": false,
            "formTag": {
              "id": 370374,
              "name": "Street 2",
              "type": "TEXT"
            }
          },
          {
            "id": 37030075,
            "mandatory": false,
            "formTag": {
              "id": 370375,
              "name": "Street 3",
              "type": "TEXT"
            }
          },
          {
            "id": 37030076,
            "mandatory": false,
            "formTag": {
              "id": 370376,
              "name": "Postal Code",
              "type": "TEXT"
            }
          },
          {
            "id": 37030077,
            "mandatory": false,
            "formTag": {
              "id": 370377,
              "name": "City",
              "type": "TEXT"
            }
          },
          {
            "id": 37030078,
            "mandatory": false,
            "formTag": {
              "id": 370378,
              "name": "District",
              "type": "TEXT"
            }
          },
          {
            "id": 37030079,
            "mandatory": false,
            "formTag": {
              "id": 370379,
              "name": "State",
              "type": "TEXT"
            }
          },
          {
            "id": 37030080,
            "mandatory": false,
            "formTag": {
              "id": 370380,
              "name": "Bank Details",
              "type": "PANEL"
            }
          },
          {
            "id": 37030081,
            "mandatory": false,
            "formTag": {
              "id": 370381,
              "name": "Please choose the option",
              "type": "EXTERNAL_DROPDOWN"
            }
          },
          {
            "id": 37030082,
            "mandatory": false,
            "formTag": {
              "id": 370382,
              "name": "Cancelled Cheque Image",
              "type": "FILE"
            }
          },
          {
            "id": 37030083,
            "mandatory": false,
            "formTag": {
              "id": 370383,
              "name": "Passbook/Bank Letter",
              "type": "FILE"
            }
          },
          {
            "id": 37030084,
            "mandatory": false,
            "formTag": {
              "id": 370384,
              "name": "Please enter IFSC and Account Number manually",
              "type": "LABEL"
            }
          },
          {
            "id": 37030085,
            "mandatory": false,
            "formTag": {
              "id": 370385,
              "name": "IFSC Code",
              "type": "TEXT"
            }
          },
          {
            "id": 37030086,
            "mandatory": false,
            "formTag": {
              "id": 370386,
              "name": "Bank Account Number",
              "type": "TEXT"
            }
          },
          {
            "id": 37030087,
            "mandatory": false,
            "formTag": {
              "id": 370387,
              "name": "Name of Account Holder",
              "type": "TEXT"
            }
          },
          {
            "id": 37030088,
            "mandatory": false,
            "formTag": {
              "id": 370388,
              "name": "Bank Name",
              "type": "TEXT"
            }
          },
          {
            "id": 37030089,
            "mandatory": false,
            "formTag": {
              "id": 370389,
              "name": "Bank Branch",
              "type": "TEXT"
            }
          },
          {
            "id": 37030090,
            "mandatory": false,
            "formTag": {
              "id": 370390,
              "name": "Bank Address",
              "type": "TEXT"
            }
          },
          {
            "id": 37030091,
            "mandatory": false,
            "formTag": {
              "id": 370391,
              "name": "Bank Country",
              "type": "TEXT"
            }
          },
          {
            "id": 37030092,
            "mandatory": false,
            "formTag": {
              "id": 370392,
              "name": "CIN and TDS Details",
              "type": "PANEL"
            }
          },
          {
            "id": 37030093,
            "mandatory": false,
            "formTag": {
              "id": 370393,
              "name": "CIN Certificate",
              "type": "FILE"
            }
          },
          {
            "id": 37030094,
            "mandatory": false,
            "formTag": {
              "id": 370394,
              "name": "CIN",
              "type": "TEXT"
            }
          },
          {
            "id": 37030095,
            "mandatory": false,
            "formTag": {
              "id": 370395,
              "name": "FDA Registration Number",
              "type": "TEXT"
            }
          },
          {
            "id": 37030096,
            "mandatory": false,
            "formTag": {
              "id": 370396,
              "name": "TDS Applicable?",
              "type": "EXTERNAL_DROPDOWN"
            }
          },
          {
            "id": 37030097,
            "mandatory": false,
            "formTag": {
              "id": 370397,
              "name": "TDS Certificate",
              "type": "FILE"
            }
          },
          {
            "id": 37030098,
            "mandatory": false,
            "formTag": {
              "id": 370398,
              "name": "MSME Details",
              "type": "PANEL"
            }
          },
          {
            "id": 37030099,
            "mandatory": false,
            "formTag": {
              "id": 370399,
              "name": "Is SSI / MSME Applicable?",
              "type": "EXTERNAL_DROPDOWN"
            }
          },
          {
            "id": 37030100,
            "mandatory": false,
            "formTag": {
              "id": 370400,
              "name": "MSME Image",
              "type": "FILE"
            }
          },
          {
            "id": 37030101,
            "mandatory": false,
            "formTag": {
              "id": 370401,
              "name": "MSME Registration Number",
              "type": "TEXT"
            }
          },
          {
            "id": 37030102,
            "mandatory": false,
            "formTag": {
              "id": 370402,
              "name": "Name",
              "type": "TEXT"
            }
          },
          {
            "id": 37030103,
            "mandatory": false,
            "formTag": {
              "id": 370403,
              "name": "Type",
              "type": "TEXT"
            }
          },
          {
            "id": 37030104,
            "mandatory": false,
            "formTag": {
              "id": 370404,
              "name": "Address",
              "type": "TEXT"
            }
          },
          {
            "id": 37030105,
            "mandatory": false,
            "formTag": {
              "id": 370405,
              "name": "Category",
              "type": "TEXT"
            }
          },
          {
            "id": 37030106,
            "mandatory": false,
            "formTag": {
              "id": 370406,
              "name": "Date",
              "type": "TEXT"
            }
          },
          {
            "id": 37030107,
            "mandatory": false,
            "formTag": {
              "id": 370407,
              "name": "Enterprise",
              "type": "TEXT"
            }
          },
          {
            "id": 37030108,
            "mandatory": false,
            "formTag": {
              "id": 370408,
              "name": "Major Activity",
              "type": "TEXT"
            }
          },
          {
            "id": 37030109,
            "mandatory": false,
            "formTag": {
              "id": 370409,
              "name": "Date of Commencement",
              "type": "TEXT"
            }
          },
          {
            "id": 37030110,
            "mandatory": false,
            "formTag": {
              "id": 370410,
              "name": "Dice Name",
              "type": "TEXT"
            }
          },
          {
            "id": 37030111,
            "mandatory": false,
            "formTag": {
              "id": 370411,
              "name": "State",
              "type": "TEXT"
            }
          },
          {
            "id": 37030112,
            "mandatory": false,
            "formTag": {
              "id": 370412,
              "name": "Applied State",
              "type": "TEXT"
            }
          },
          {
            "id": 37030113,
            "mandatory": false,
            "formTag": {
              "id": 370413,
              "name": "Modified Date",
              "type": "TEXT"
            }
          },
          {
            "id": 37030114,
            "mandatory": false,
            "formTag": {
              "id": 370414,
              "name": "Expiry Date",
              "type": "TEXT"
            }
          },
          {
            "id": 37030115,
            "mandatory": false,
            "formTag": {
              "id": 370415,
              "name": "Address Line1",
              "type": "TEXT"
            }
          },
          {
            "id": 37030116,
            "mandatory": false,
            "formTag": {
              "id": 370416,
              "name": "Building",
              "type": "TEXT"
            }
          },
          {
            "id": 37030117,
            "mandatory": false,
            "formTag": {
              "id": 370417,
              "name": "Street",
              "type": "TEXT"
            }
          },
          {
            "id": 37030118,
            "mandatory": false,
            "formTag": {
              "id": 370418,
              "name": "Area",
              "type": "TEXT"
            }
          },
          {
            "id": 37030119,
            "mandatory": false,
            "formTag": {
              "id": 370419,
              "name": "City",
              "type": "TEXT"
            }
          },
          {
            "id": 37030120,
            "mandatory": false,
            "formTag": {
              "id": 370420,
              "name": "Pin",
              "type": "TEXT"
            }
          },
          {
            "id": 37030121,
            "mandatory": false,
            "formTag": {
              "id": 370421,
              "name": "State",
              "type": "TEXT"
            }
          },
          {
            "id": 37030122,
            "mandatory": false,
            "formTag": {
              "id": 370422,
              "name": "District",
              "type": "TEXT"
            }
          },
          {
            "id": 37030123,
            "mandatory": false,
            "formTag": {
              "id": 370423,
              "name": "Classification Year",
              "type": "TEXT"
            }
          },
          {
            "id": 37030124,
            "mandatory": false,
            "formTag": {
              "id": 370424,
              "name": "Classification Date",
              "type": "TEXT"
            }
          },
          {
            "id": 37030125,
            "mandatory": false,
            "formTag": {
              "id": 370425,
              "name": "MSME Declaration",
              "type": "FILE"
            }
          },
          {
            "id": 37030126,
            "mandatory": false,
            "formTag": {
              "id": 370426,
              "name": "Vendor Duplicity Details",
              "type": "PANEL"
            }
          },
          {
            "id": 37030127,
            "mandatory": false,
            "formTag": {
              "id": 370427,
              "name": "Exception Duplicate Vendor creation",
              "type": "STATIC_CHECKBOX"
            }
          },
          {
            "id": 37030128,
            "mandatory": false,
            "formTag": {
              "id": 370428,
              "name": "Duplicate Vendor Number",
              "type": "TEXT"
            }
          },
          {
            "id": 37030129,
            "mandatory": false,
            "formTag": {
              "id": 370429,
              "name": "Duplicate Vendor Description",
              "type": "TEXT"
            }
          },
          {
            "id": 37030130,
            "mandatory": false,
            "formTag": {
              "id": 370430,
              "name": "Block status",
              "type": "TEXT"
            }
          },
          {
            "id": 37030131,
            "mandatory": false,
            "formTag": {
              "id": 370431,
              "name": "Duplicate GST Result",
              "type": "TEXT"
            }
          },
          {
            "id": 37030132,
            "mandatory": false,
            "formTag": {
              "id": 370432,
              "name": "Duplicate PAN Result",
              "type": "TEXT"
            }
          },
          {
            "id": 37030133,
            "mandatory": false,
            "formTag": {
              "id": 370433,
              "name": "Duplicate Email Result",
              "type": "TEXT"
            }
          },
          {
            "id": 37030134,
            "mandatory": false,
            "formTag": {
              "id": 370434,
              "name": "Duplicate Mobile Result",
              "type": "TEXT"
            }
          },
          {
            "id": 37030135,
            "mandatory": false,
            "formTag": {
              "id": 370435,
              "name": "Duplicate Bank Account Number Result",
              "type": "TEXT"
            }
          },
          {
            "id": 37030136,
            "mandatory": false,
            "formTag": {
              "id": 370436,
              "name": "Justification for Duplicate Vendor Creation",
              "type": "TEXT"
            }
          },
          {
            "id": 37030137,
            "mandatory": false,
            "formTag": {
              "id": 370437,
              "name": "Comments",
              "type": "TEXT"
            }
          },
          {
            "id": 37030138,
            "mandatory": false,
            "formTag": {
              "id": 370438,
              "name": "Purchase Organization Details",
              "type": "PANEL"
            }
          },
          {
            "id": 37030139,
            "mandatory": false,
            "formTag": {
              "id": 370439,
              "name": "Company Code",
              "type": "DROPDOWN"
            }
          },
          {
            "id": 37030140,
            "mandatory": false,
            "formTag": {
              "id": 370440,
              "name": "Order currency",
              "type": "DROPDOWN"
            }
          },
          {
            "id": 37030141,
            "mandatory": true,
            "formTag": {
              "id": 370441,
              "name": "Purchase Organization",
              "type": "MULTI_DROPDOWN"
            }
          },
          {
            "id": 37030142,
            "mandatory": true,
            "formTag": {
              "id": 370442,
              "name": "Terms of Payment",
              "type": "DROPDOWN"
            }
          },
          {
            "id": 37030143,
            "mandatory": false,
            "formTag": {
              "id": 370443,
              "name": "Incoterms",
              "type": "DROPDOWN"
            }
          },
          {
            "id": 37030144,
            "mandatory": false,
            "formTag": {
              "id": 370444,
              "name": "Incoterms (Part 2)",
              "type": "DROPDOWN"
            }
          },
          {
            "id": 37030145,
            "mandatory": false,
            "formTag": {
              "id": 370445,
              "name": "GR-Based Inv. Verif.",
              "type": "TEXT"
            }
          },
          {
            "id": 37030146,
            "mandatory": false,
            "formTag": {
              "id": 370446,
              "name": "Schema Grp, Supplier",
              "type": "TEXT"
            }
          },
          {
            "id": 37030147,
            "mandatory": false,
            "formTag": {
              "id": 370447,
              "name": "Automatic PO",
              "type": "TEXT"
            }
          },
          {
            "id": 37030148,
            "mandatory": false,
            "formTag": {
              "id": 370448,
              "name": "Service-Based Invoice Verification",
              "type": "CHECKBOX"
            }
          },
          {
            "id": 37030149,
            "mandatory": false,
            "formTag": {
              "id": 370449,
              "name": "Payment Details",
              "type": "PANEL"
            }
          },
          {
            "id": 37030150,
            "mandatory": true,
            "formTag": {
              "id": 370450,
              "name": "Payment Methods",
              "type": "TEXT"
            }
          },
          {
            "id": 37030151,
            "mandatory": false,
            "formTag": {
              "id": 370451,
              "name": "House Bank",
              "type": "DROPDOWN"
            }
          },
          {
            "id": 37030152,
            "mandatory": false,
            "formTag": {
              "id": 370452,
              "name": "Minority Indicator",
              "type": "TEXT"
            }
          },
          {
            "id": 37030153,
            "mandatory": false,
            "formTag": {
              "id": 370453,
              "name": "VENDOR INVOICE",
              "type": "FILE"
            }
          },
          {
            "id": 37030154,
            "mandatory": true,
            "formTag": {
              "id": 370454,
              "name": "Reconciliation acct",
              "type": "DROPDOWN"
            }
          },
          {
            "id": 37030155,
            "mandatory": true,
            "formTag": {
              "id": 370455,
              "name": "Currency",
              "type": "DROPDOWN"
            }
          },
          {
            "id": 37030156,
            "mandatory": true,
            "formTag": {
              "id": 370456,
              "name": "Is Vendor Your Customer?",
              "type": "DROPDOWN"
            }
          },
          {
            "id": 37030157,
            "mandatory": false,
            "formTag": {
              "id": 370457,
              "name": "Customer Code",
              "type": "TEXT"
            }
          },
          {
            "id": 37030158,
            "mandatory": false,
            "formTag": {
              "id": 370458,
              "name": "Service Tax File",
              "type": "FILE"
            }
          },
          {
            "id": 37030159,
            "mandatory": false,
            "formTag": {
              "id": 370459,
              "name": "Share with",
              "type": "TEXT"
            }
          },
          {
            "id": 37030160,
            "mandatory": false,
            "formTag": {
              "id": 370460,
              "name": "Additional File",
              "type": "FILE"
            }
          },
          {
            "id": 37030161,
            "mandatory": false,
            "formTag": {
              "id": 370461,
              "name": "Withholding Tax Details",
              "type": "PANEL"
            }
          },
          {
            "id": 37030162,
            "mandatory": true,
            "formTag": {
              "id": 370462,
              "name": "Withholding Tax Type",
              "type": "DROPDOWN"
            }
          },
          {
            "id": 37030163,
            "mandatory": true,
            "formTag": {
              "id": 370463,
              "name": "Subject to w/tax",
              "type": "CHECKBOX"
            }
          },
          {
            "id": 37030164,
            "mandatory": false,
            "formTag": {
              "id": 370464,
              "name": "Recipient Type",
              "type": "TEXT"
            }
          },
          {
            "id": 37030165,
            "mandatory": true,
            "formTag": {
              "id": 370465,
              "name": "Withholding Tax Code",
              "type": "DROPDOWN"
            }
          },
          {
            "id": 37030166,
            "mandatory": true,
            "formTag": {
              "id": 370466,
              "name": "All financial & bank details are verified",
              "type": "CHECKBOX"
            }
          },
          {
            "id": 37030167,
            "mandatory": false,
            "formTag": {
              "id": 370467,
              "name": "Basic Details",
              "type": "PANEL"
            }
          },
          {
            "id": 37030168,
            "mandatory": false,
            "formTag": {
              "id": 370468,
              "name": "Search term / Reference Number(Transaction ID)",
              "type": "TEXT"
            }
          },
          {
            "id": 37030169,
            "mandatory": false,
            "formTag": {
              "id": 370469,
              "name": "Created on",
              "type": "DATE"
            }
          },
          {
            "id": 37030170,
            "mandatory": false,
            "formTag": {
              "id": 370470,
              "name": "Created By",
              "type": "TEXT"
            }
          },
          {
            "id": 37030171,
            "mandatory": true,
            "formTag": {
              "id": 370471,
              "name": "Name/ First Name of the Organisation",
              "type": "TEXT"
            }
          },
          {
            "id": 37030172,
            "mandatory": true,
            "formTag": {
              "id": 370472,
              "name": "Select the process type",
              "type": "DROPDOWN"
            }
          },
          {
            "id": 37030173,
            "mandatory": false,
            "formTag": {
              "id": 370473,
              "name": "Process Type",
              "type": "TEXT"
            }
          },
          {
            "id": 37030174,
            "mandatory": true,
            "formTag": {
              "id": 370474,
              "name": "Account Group/Vendor Type",
              "type": "DROPDOWN"
            }
          },
          {
            "id": 37030175,
            "mandatory": true,
            "formTag": {
              "id": 370475,
              "name": "Group key/Corporate Group",
              "type": "DROPDOWN"
            }
          },
          {
            "id": 37030176,
            "mandatory": true,
            "formTag": {
              "id": 370476,
              "name": "Vendor Domestic or Import",
              "type": "TEXT"
            }
          },
          {
            "id": 37030177,
            "mandatory": true,
            "formTag": {
              "id": 370477,
              "name": "Country",
              "type": "DROPDOWN"
            }
          },
          {
            "id": 37030178,
            "mandatory": false,
            "formTag": {
              "id": 370478,
              "name": "Country Name",
              "type": "TEXT"
            }
          },
          {
            "id": 37030179,
            "mandatory": false,
            "formTag": {
              "id": 370479,
              "name": "Country Code",
              "type": "TEXT"
            }
          },
          {
            "id": 37030180,
            "mandatory": true,
            "formTag": {
              "id": 370480,
              "name": "Company Code",
              "type": "DROPDOWN"
            }
          },
          {
            "id": 37030181,
            "mandatory": true,
            "formTag": {
              "id": 370481,
              "name": "Mobile Number",
              "type": "MOBILE"
            }
          },
          {
            "id": 37030182,
            "mandatory": true,
            "formTag": {
              "id": 370482,
              "name": "Email",
              "type": "EMAIL"
            }
          },
          {
            "id": 37030183,
            "mandatory": true,
            "formTag": {
              "id": 370483,
              "name": "Vendor Contact Name",
              "type": "TEXT"
            }
          },
          {
            "id": 37030184,
            "mandatory": false,
            "formTag": {
              "id": 370484,
              "name": "Basic Details",
              "type": "PANEL"
            }
          },
          {
            "id": 37030185,
            "mandatory": false,
            "formTag": {
              "id": 370485,
              "name": "Search term / Reference Number(Transaction ID)",
              "type": "TEXT"
            }
          },
          {
            "id": 37030186,
            "mandatory": false,
            "formTag": {
              "id": 370486,
              "name": "Created on",
              "type": "DATE"
            }
          },
          {
            "id": 37030187,
            "mandatory": false,
            "formTag": {
              "id": 370487,
              "name": "Created By",
              "type": "TEXT"
            }
          },
          {
            "id": 37030188,
            "mandatory": true,
            "formTag": {
              "id": 370488,
              "name": "Name/ First Name of the Organization",
              "type": "TEXT"
            }
          },
          {
            "id": 37030189,
            "mandatory": true,
            "formTag": {
              "id": 370489,
              "name": "Select the process type",
              "type": "DROPDOWN"
            }
          },
          {
            "id": 37030190,
            "mandatory": false,
            "formTag": {
              "id": 370490,
              "name": "Process Type",
              "type": "TEXT"
            }
          },
          {
            "id": 37030191,
            "mandatory": true,
            "formTag": {
              "id": 370491,
              "name": "Account Group/Vendor Type",
              "type": "DROPDOWN"
            }
          },
          {
            "id": 37030192,
            "mandatory": true,
            "formTag": {
              "id": 370492,
              "name": "Group key/Corporate Group",
              "type": "DROPDOWN"
            }
          },
          {
            "id": 37030193,
            "mandatory": true,
            "formTag": {
              "id": 370493,
              "name": "Vendor Domestic or Import",
              "type": "TEXT"
            }
          },
          {
            "id": 37030194,
            "mandatory": true,
            "formTag": {
              "id": 370494,
              "name": "Country",
              "type": "DROPDOWN"
            }
          },
          {
            "id": 37030195,
            "mandatory": false,
            "formTag": {
              "id": 370495,
              "name": "Country Name",
              "type": "TEXT"
            }
          },
          {
            "id": 37030196,
            "mandatory": false,
            "formTag": {
              "id": 370496,
              "name": "Country Code",
              "type": "TEXT"
            }
          },
          {
            "id": 37030197,
            "mandatory": true,
            "formTag": {
              "id": 370497,
              "name": "Company Code",
              "type": "DROPDOWN"
            }
          },
          {
            "id": 37030198,
            "mandatory": true,
            "formTag": {
              "id": 370498,
              "name": "Mobile Number",
              "type": "MOBILE"
            }
          },
          {
            "id": 37030199,
            "mandatory": false,
            "formTag": {
              "id": 370499,
              "name": "Do you wish to add additional mobile numbers (India)?",
              "type": "EXTERNAL_DROPDOWN"
            }
          },
          {
            "id": 37030200,
            "mandatory": false,
            "formTag": {
              "id": 370500,
              "name": "Do you wish to add additional mobile numbers (Non-India)?",
              "type": "EXTERNAL_DROPDOWN"
            }
          },
          {
            "id": 37030201,
            "mandatory": false,
            "formTag": {
              "id": 370501,
              "name": "Mobile Number 2 (Domestic)",
              "type": "TEXT"
            }
          },
          {
            "id": 37030202,
            "mandatory": false,
            "formTag": {
              "id": 370502,
              "name": "Mobile Number 3 (Domestic)",
              "type": "TEXT"
            }
          },
          {
            "id": 37030203,
            "mandatory": false,
            "formTag": {
              "id": 370503,
              "name": "Mobile Number 4 (Domestic)",
              "type": "TEXT"
            }
          },
          {
            "id": 37030204,
            "mandatory": false,
            "formTag": {
              "id": 370504,
              "name": "Mobile Number 5 (Domestic)",
              "type": "TEXT"
            }
          },
          {
            "id": 37030205,
            "mandatory": false,
            "formTag": {
              "id": 370505,
              "name": "Mobile Number 2 (Import)",
              "type": "TEXT"
            }
          },
          {
            "id": 37030206,
            "mandatory": false,
            "formTag": {
              "id": 370506,
              "name": "Mobile Number 3 (Import)",
              "type": "TEXT"
            }
          },
          {
            "id": 37030207,
            "mandatory": false,
            "formTag": {
              "id": 370507,
              "name": "Mobile Number 4 (Import)",
              "type": "TEXT"
            }
          },
          {
            "id": 37030208,
            "mandatory": false,
            "formTag": {
              "id": 370508,
              "name": "Mobile Number 5 (Import)",
              "type": "TEXT"
            }
          },
          {
            "id": 37030209,
            "mandatory": true,
            "formTag": {
              "id": 370509,
              "name": "Vendor Contact Email",
              "type": "TEXT"
            }
          },
          {
            "id": 37030210,
            "mandatory": true,
            "formTag": {
              "id": 370510,
              "name": "Vendor Contact Name",
              "type": "TEXT"
            }
          },
          {
            "id": 37030211,
            "mandatory": false,
            "formTag": {
              "id": 370511,
              "name": "Do you wish to add additional email addresses?",
              "type": "EXTERNAL_DROPDOWN"
            }
          },
          {
            "id": 37030212,
            "mandatory": false,
            "formTag": {
              "id": 370512,
              "name": "Email 2",
              "type": "TEXT"
            }
          },
          {
            "id": 37030213,
            "mandatory": false,
            "formTag": {
              "id": 370513,
              "name": "Concerned email addresses?",
              "type": "EXTERNAL_DROPDOWN"
            }
          },
          {
            "id": 37030214,
            "mandatory": false,
            "formTag": {
              "id": 370514,
              "name": "Email ID",
              "type": "TEXT"
            }
          },
          {
            "id": 37030215,
            "mandatory": false,
            "formTag": {
              "id": 370515,
              "name": "PAN and GST Details",
              "type": "PANEL"
            }
          },
          {
            "id": 37030216,
            "mandatory": false,
            "formTag": {
              "id": 370516,
              "name": "PAN DETAILS",
              "type": "LABEL"
            }
          },
          {
            "id": 37030217,
            "mandatory": false,
            "formTag": {
              "id": 370517,
              "name": "Upload PAN",
              "type": "FILE"
            }
          },
          {
            "id": 37030218,
            "mandatory": false,
            "formTag": {
              "id": 370518,
              "name": "PAN",
              "type": "TEXT"
            }
          },
          {
            "id": 37030219,
            "mandatory": false,
            "formTag": {
              "id": 370519,
              "name": "Pan Holder Name",
              "type": "TEXT"
            }
          },
          {
            "id": 37030220,
            "mandatory": false,
            "formTag": {
              "id": 370520,
              "name": "PAN Type",
              "type": "TEXT"
            }
          },
          {
            "id": 37030221,
            "mandatory": false,
            "formTag": {
              "id": 370521,
              "name": "PAN Status",
              "type": "TEXT"
            }
          },
          {
            "id": 37030222,
            "mandatory": false,
            "formTag": {
              "id": 370522,
              "name": "Aadhaar PAN List Status",
              "type": "TEXT"
            }
          },
          {
            "id": 37030223,
            "mandatory": false,
            "formTag": {
              "id": 370523,
              "name": "GST Details",
              "type": "LABEL"
            }
          },
          {
            "id": 37030224,
            "mandatory": false,
            "formTag": {
              "id": 370524,
              "name": "Please select GST option",
              "type": "EXTERNAL_DROPDOWN"
            }
          },
          {
            "id": 37030225,
            "mandatory": false,
            "formTag": {
              "id": 370525,
              "name": "GSTIN IMAGE",
              "type": "FILE"
            }
          },
          {
            "id": 37030226,
            "mandatory": false,
            "formTag": {
              "id": 370526,
              "name": "GSTIN",
              "type": "TEXT"
            }
          },
          {
            "id": 37030227,
            "mandatory": false,
            "formTag": {
              "id": 370527,
              "name": "Trade Name",
              "type": "TEXT"
            }
          },
          {
            "id": 37030228,
            "mandatory": false,
            "formTag": {
              "id": 370528,
              "name": "Legal Name",
              "type": "TEXT"
            }
          },
          {
            "id": 37030229,
            "mandatory": false,
            "formTag": {
              "id": 370529,
              "name": "Reg Date",
              "type": "TEXT"
            }
          },
          {
            "id": 37030230,
            "mandatory": false,
            "formTag": {
              "id": 370530,
              "name": "Type",
              "type": "TEXT"
            }
          },
          {
            "id": 37030231,
            "mandatory": false,
            "formTag": {
              "id": 370531,
              "name": "Building Number",
              "type": "TEXT"
            }
          },
          {
            "id": 37030232,
            "mandatory": false,
            "formTag": {
              "id": 370532,
              "name": "Street",
              "type": "TEXT"
            }
          },
          {
            "id": 37030233,
            "mandatory": false,
            "formTag": {
              "id": 370533,
              "name": "City",
              "type": "TEXT"
            }
          },
          {
            "id": 37030234,
            "mandatory": false,
            "formTag": {
              "id": 370534,
              "name": "District",
              "type": "TEXT"
            }
          },
          {
            "id": 37030235,
            "mandatory": false,
            "formTag": {
              "id": 370535,
              "name": "State",
              "type": "TEXT"
            }
          },
          {
            "id": 37030236,
            "mandatory": false,
            "formTag": {
              "id": 370536,
              "name": "Pin Code",
              "type": "TEXT"
            }
          },
          {
            "id": 37030237,
            "mandatory": false,
            "formTag": {
              "id": 370537,
              "name": "Upload Declaration",
              "type": "FILE"
            }
          },
          {
            "id": 37030238,
            "mandatory": false,
            "formTag": {
              "id": 370538,
              "name": "GST Vendor Classification",
              "type": "TEXT"
            }
          },
          {
            "id": 37030239,
            "mandatory": false,
            "formTag": {
              "id": 370539,
              "name": "ID Type",
              "type": "TEXT"
            }
          },
          {
            "id": 37030240,
            "mandatory": false,
            "formTag": {
              "id": 370540,
              "name": "Service Tax Registration Number",
              "type": "TEXT"
            }
          },
          {
            "id": 37030241,
            "mandatory": false,
            "formTag": {
              "id": 370541,
              "name": "Language Key",
              "type": "TEXT"
            }
          },
          {
            "id": 37030242,
            "mandatory": false,
            "formTag": {
              "id": 370542,
              "name": "Vendor Basic Details",
              "type": "PANEL"
            }
          },
          {
            "id": 37030243,
            "mandatory": false,
            "formTag": {
              "id": 370543,
              "name": "Name/ First Name of the Organization",
              "type": "TEXT"
            }
          },
          {
            "id": 37030244,
            "mandatory": false,
            "formTag": {
              "id": 370544,
              "name": "Name/ Middle Name of the Organization",
              "type": "TEXT"
            }
          },
          {
            "id": 37030245,
            "mandatory": false,
            "formTag": {
              "id": 370545,
              "name": "Name/ Last Name of the Organization",
              "type": "TEXT"
            }
          },
          {
            "id": 37030246,
            "mandatory": false,
            "formTag": {
              "id": 370546,
              "name": "Name 4/Alternate Name",
              "type": "TEXT"
            }
          },
          {
            "id": 37030247,
            "mandatory": false,
            "formTag": {
              "id": 370547,
              "name": "Title",
              "type": "EXTERNAL_DROPDOWN"
            }
          },
          {
            "id": 37030248,
            "mandatory": false,
            "formTag": {
              "id": 370548,
              "name": "Business Registration Number Available?",
              "type": "EXTERNAL_DROPDOWN"
            }
          },
          {
            "id": 37030249,
            "mandatory": false,
            "formTag": {
              "id": 370549,
              "name": "Business Registration Number",
              "type": "TEXT"
            }
          },
          {
            "id": 37030250,
            "mandatory": false,
            "formTag": {
              "id": 370550,
              "name": "Address Details",
              "type": "PANEL"
            }
          },
          {
            "id": 37030251,
            "mandatory": false,
            "formTag": {
              "id": 370551,
              "name": "Please Choose Address Proof",
              "type": "EXTERNAL_DROPDOWN"
            }
          },
          {
            "id": 37030252,
            "mandatory": false,
            "formTag": {
              "id": 370552,
              "name": "Electricity bill copy",
              "type": "FILE"
            }
          },
          {
            "id": 37030253,
            "mandatory": false,
            "formTag": {
              "id": 370553,
              "name": "Aadhaar Front copy",
              "type": "FILE"
            }
          },
          {
            "id": 37030254,
            "mandatory": false,
            "formTag": {
              "id": 370554,
              "name": "Aadhaar Back Image",
              "type": "FILE"
            }
          },
          {
            "id": 37030255,
            "mandatory": false,
            "formTag": {
              "id": 370555,
              "name": "Street",
              "type": "TEXT"
            }
          },
          {
            "id": 37030256,
            "mandatory": false,
            "formTag": {
              "id": 370556,
              "name": "Street 1",
              "type": "TEXT"
            }
          },
          {
            "id": 37030257,
            "mandatory": false,
            "formTag": {
              "id": 370557,
              "name": "Street 2",
              "type": "TEXT"
            }
          },
          {
            "id": 37030258,
            "mandatory": false,
            "formTag": {
              "id": 370558,
              "name": "Street 3",
              "type": "TEXT"
            }
          },
          {
            "id": 37030259,
            "mandatory": false,
            "formTag": {
              "id": 370559,
              "name": "Postal Code",
              "type": "TEXT"
            }
          },
          {
            "id": 37030260,
            "mandatory": false,
            "formTag": {
              "id": 370560,
              "name": "City",
              "type": "TEXT"
            }
          },
          {
            "id": 37030261,
            "mandatory": false,
            "formTag": {
              "id": 370561,
              "name": "District",
              "type": "TEXT"
            }
          },
          {
            "id": 37030262,
            "mandatory": false,
            "formTag": {
              "id": 370562,
              "name": "State",
              "type": "TEXT"
            }
          },
          {
            "id": 37030263,
            "mandatory": false,
            "formTag": {
              "id": 370563,
              "name": "Bank Details",
              "type": "PANEL"
            }
          },
          {
            "id": 37030264,
            "mandatory": false,
            "formTag": {
              "id": 370564,
              "name": "Please choose the option",
              "type": "EXTERNAL_DROPDOWN"
            }
          },
          {
            "id": 37030265,
            "mandatory": false,
            "formTag": {
              "id": 370565,
              "name": "Cancelled Cheque Image",
              "type": "FILE"
            }
          },
          {
            "id": 37030266,
            "mandatory": false,
            "formTag": {
              "id": 370566,
              "name": "Passbook/Bank Letter",
              "type": "FILE"
            }
          },
          {
            "id": 37030267,
            "mandatory": false,
            "formTag": {
              "id": 370567,
              "name": "Please enter IFSC and Account Number manually",
              "type": "LABEL"
            }
          },
          {
            "id": 37030268,
            "mandatory": false,
            "formTag": {
              "id": 370568,
              "name": "IFSC Code",
              "type": "TEXT"
            }
          },
          {
            "id": 37030269,
            "mandatory": false,
            "formTag": {
              "id": 370569,
              "name": "Bank Account Number",
              "type": "TEXT"
            }
          },
          {
            "id": 37030270,
            "mandatory": false,
            "formTag": {
              "id": 370570,
              "name": "Name of Account Holder",
              "type": "TEXT"
            }
          },
          {
            "id": 37030271,
            "mandatory": false,
            "formTag": {
              "id": 370571,
              "name": "Bank Name",
              "type": "TEXT"
            }
          },
          {
            "id": 37030272,
            "mandatory": false,
            "formTag": {
              "id": 370572,
              "name": "Bank Branch",
              "type": "TEXT"
            }
          },
          {
            "id": 37030273,
            "mandatory": false,
            "formTag": {
              "id": 370573,
              "name": "Bank Address",
              "type": "TEXT"
            }
          },
          {
            "id": 37030274,
            "mandatory": false,
            "formTag": {
              "id": 370574,
              "name": "Bank Country",
              "type": "TEXT"
            }
          },
          {
            "id": 37030275,
            "mandatory": false,
            "formTag": {
              "id": 370575,
              "name": "CIN and TDS Details",
              "type": "PANEL"
            }
          },
          {
            "id": 37030276,
            "mandatory": false,
            "formTag": {
              "id": 370576,
              "name": "CIN Certificate",
              "type": "FILE"
            }
          },
          {
            "id": 37030277,
            "mandatory": false,
            "formTag": {
              "id": 370577,
              "name": "CIN",
              "type": "TEXT"
            }
          },
          {
            "id": 37030278,
            "mandatory": false,
            "formTag": {
              "id": 370578,
              "name": "FDA Registration Number",
              "type": "TEXT"
            }
          },
          {
            "id": 37030279,
            "mandatory": false,
            "formTag": {
              "id": 370579,
              "name": "TDS Applicable?",
              "type": "EXTERNAL_DROPDOWN"
            }
          },
          {
            "id": 37030280,
            "mandatory": false,
            "formTag": {
              "id": 370580,
              "name": "TDS Certificate",
              "type": "FILE"
            }
          },
          {
            "id": 37030281,
            "mandatory": false,
            "formTag": {
              "id": 370581,
              "name": "MSME Details",
              "type": "PANEL"
            }
          },
          {
            "id": 37030282,
            "mandatory": false,
            "formTag": {
              "id": 370582,
              "name": "Is SSI / MSME Applicable?",
              "type": "EXTERNAL_DROPDOWN"
            }
          },
          {
            "id": 37030283,
            "mandatory": false,
            "formTag": {
              "id": 370583,
              "name": "MSME Image",
              "type": "FILE"
            }
          },
          {
            "id": 37030284,
            "mandatory": false,
            "formTag": {
              "id": 370584,
              "name": "MSME Registration Number",
              "type": "TEXT"
            }
          },
          {
            "id": 37030285,
            "mandatory": false,
            "formTag": {
              "id": 370585,
              "name": "Name",
              "type": "TEXT"
            }
          },
          {
            "id": 37030286,
            "mandatory": false,
            "formTag": {
              "id": 370586,
              "name": "Type",
              "type": "TEXT"
            }
          },
          {
            "id": 37030287,
            "mandatory": false,
            "formTag": {
              "id": 370587,
              "name": "Address",
              "type": "TEXT"
            }
          },
          {
            "id": 37030288,
            "mandatory": false,
            "formTag": {
              "id": 370588,
              "name": "Category",
              "type": "TEXT"
            }
          },
          {
            "id": 37030289,
            "mandatory": false,
            "formTag": {
              "id": 370589,
              "name": "Date",
              "type": "TEXT"
            }
          },
          {
            "id": 37030290,
            "mandatory": false,
            "formTag": {
              "id": 370590,
              "name": "Enterprise",
              "type": "TEXT"
            }
          },
          {
            "id": 37030291,
            "mandatory": false,
            "formTag": {
              "id": 370591,
              "name": "Major Activity",
              "type": "TEXT"
            }
          },
          {
            "id": 37030292,
            "mandatory": false,
            "formTag": {
              "id": 370592,
              "name": "Date of Commencement",
              "type": "TEXT"
            }
          },
          {
            "id": 37030293,
            "mandatory": false,
            "formTag": {
              "id": 370593,
              "name": "Dic Name",
              "type": "TEXT"
            }
          },
          {
            "id": 37030294,
            "mandatory": false,
            "formTag": {
              "id": 370594,
              "name": "State",
              "type": "TEXT"
            }
          },
          {
            "id": 37030295,
            "mandatory": false,
            "formTag": {
              "id": 370595,
              "name": "Applied State",
              "type": "TEXT"
            }
          },
          {
            "id": 37030296,
            "mandatory": false,
            "formTag": {
              "id": 370596,
              "name": "Modified Date",
              "type": "TEXT"
            }
          },
          {
            "id": 37030297,
            "mandatory": false,
            "formTag": {
              "id": 370597,
              "name": "Expiry Date",
              "type": "TEXT"
            }
          },
          {
            "id": 37030298,
            "mandatory": false,
            "formTag": {
              "id": 370598,
              "name": "Address Line1",
              "type": "TEXT"
            }
          },
          {
            "id": 37030299,
            "mandatory": false,
            "formTag": {
              "id": 370599,
              "name": "Building",
              "type": "TEXT"
            }
          },
          {
            "id": 37030300,
            "mandatory": false,
            "formTag": {
              "id": 370600,
              "name": "Street",
              "type": "TEXT"
            }
          },
          {
            "id": 37030301,
            "mandatory": false,
            "formTag": {
              "id": 370601,
              "name": "Area",
              "type": "TEXT"
            }
          },
          {
            "id": 37030302,
            "mandatory": false,
            "formTag": {
              "id": 370602,
              "name": "City",
              "type": "TEXT"
            }
          },
          {
            "id": 37030303,
            "mandatory": false,
            "formTag": {
              "id": 370603,
              "name": "Pin",
              "type": "TEXT"
            }
          },
          {
            "id": 37030304,
            "mandatory": false,
            "formTag": {
              "id": 370604,
              "name": "State",
              "type": "TEXT"
            }
          },
          {
            "id": 37030305,
            "mandatory": false,
            "formTag": {
              "id": 370605,
              "name": "District",
              "type": "TEXT"
            }
          },
          {
            "id": 37030306,
            "mandatory": false,
            "formTag": {
              "id": 370606,
              "name": "Classification Year",
              "type": "TEXT"
            }
          },
          {
            "id": 37030307,
            "mandatory": false,
            "formTag": {
              "id": 370607,
              "name": "Classification Date",
              "type": "TEXT"
            }
          },
          {
            "id": 37030308,
            "mandatory": false,
            "formTag": {
              "id": 370608,
              "name": "MSME Declaration",
              "type": "FILE"
            }
          },
          {
            "id": 37030309,
            "mandatory": false,
            "formTag": {
              "id": 370609,
              "name": "Exception Duplicate Vendor creation",
              "type": "STATIC_CHECKBOX"
            }
          },
          {
            "id": 37030310,
            "mandatory": false,
            "formTag": {
              "id": 370610,
              "name": "Duplicate Vendor Number",
              "type": "TEXT"
            }
          },
          {
            "id": 37030311,
            "mandatory": false,
            "formTag": {
              "id": 370611,
              "name": "Duplicate Vendor Description",
              "type": "TEXT"
            }
          },
          {
            "id": 37030312,
            "mandatory": false,
            "formTag": {
              "id": 370612,
              "name": "Block status",
              "type": "TEXT"
            }
          },
          {
            "id": 37030313,
            "mandatory": false,
            "formTag": {
              "id": 370613,
              "name": "Duplicate GST Result",
              "type": "TEXT"
            }
          },
          {
            "id": 37030314,
            "mandatory": false,
            "formTag": {
              "id": 370614,
              "name": "Duplicate PAN Result",
              "type": "TEXT"
            }
          },
          {
            "id": 37030315,
            "mandatory": false,
            "formTag": {
              "id": 370615,
              "name": "Duplicate Email Result",
              "type": "TEXT"
            }
          },
          {
            "id": 37030316,
            "mandatory": false,
            "formTag": {
              "id": 370616,
              "name": "Duplicate Mobile Result",
              "type": "TEXT"
            }
          },
          {
            "id": 37030317,
            "mandatory": false,
            "formTag": {
              "id": 370617,
              "name": "Duplicate Bank Account Number Result",
              "type": "TEXT"
            }
          },
          {
            "id": 37030318,
            "mandatory": false,
            "formTag": {
              "id": 370618,
              "name": "Justification for Duplicate Vendor Creation",
              "type": "TEXT"
            }
          },
          {
            "id": 37030319,
            "mandatory": false,
            "formTag": {
              "id": 370619,
              "name": "Comments",
              "type": "TEXT"
            }
          },
          {
            "id": 37030320,
            "mandatory": false,
            "formTag": {
              "id": 370620,
              "name": "Purchase Organization Details",
              "type": "PANEL"
            }
          },
          {
            "id": 37030321,
            "mandatory": false,
            "formTag": {
              "id": 370621,
              "name": "Company Code",
              "type": "DROPDOWN"
            }
          },
          {
            "id": 37030322,
            "mandatory": false,
            "formTag": {
              "id": 370622,
              "name": "Order currency",
              "type": "DROPDOWN"
            }
          },
          {
            "id": 37030323,
            "mandatory": true,
            "formTag": {
              "id": 370623,
              "name": "Purchase Organization",
              "type": "MULTI_DROPDOWN"
            }
          },
          {
            "id": 37030324,
            "mandatory": true,
            "formTag": {
              "id": 370624,
              "name": "Terms of Payment",
              "type": "DROPDOWN"
            }
          },
          {
            "id": 37030325,
            "mandatory": false,
            "formTag": {
              "id": 370625,
              "name": "Incoterms",
              "type": "DROPDOWN"
            }
          },
          {
            "id": 37030326,
            "mandatory": false,
            "formTag": {
              "id": 370626,
              "name": "Incoterms (Part 2)",
              "type": "DROPDOWN"
            }
          },
          {
            "id": 37030327,
            "mandatory": false,
            "formTag": {
              "id": 370627,
              "name": "GR-Based Inv. Verify.",
              "type": "TEXT"
            }
          },
          {
            "id": 37030328,
            "mandatory": false,
            "formTag": {
              "id": 370628,
              "name": "Schema Grp, Supplier",
              "type": "TEXT"
            }
          },
          {
            "id": 37030329,
            "mandatory": false,
            "formTag": {
              "id": 370629,
              "name": "Automatic PO",
              "type": "TEXT"
            }
          },
          {
            "id": 37030330,
            "mandatory": false,
            "formTag": {
              "id": 370630,
              "name": "Service-Based Invoice Verification",
              "type": "CHECKBOX"
            }
          },
          {
            "id": 37030331,
            "mandatory": false,
            "formTag": {
              "id": 370631,
              "name": "Payment Details",
              "type": "PANEL"
            }
          },
          {
            "id": 37030332,
            "mandatory": true,
            "formTag": {
              "id": 370632,
              "name": "Payment Methods",
              "type": "TEXT"
            }
          },
          {
            "id": 37030333,
            "mandatory": false,
            "formTag": {
              "id": 370633,
              "name": "House Bank",
              "type": "DROPDOWN"
            }
          },
          {
            "id": 37030334,
            "mandatory": false,
            "formTag": {
              "id": 370634,
              "name": "Minority Indicator",
              "type": "TEXT"
            }
          },
          {
            "id": 37030335,
            "mandatory": false,
            "formTag": {
              "id": 370635,
              "name": "VENDOR INVOICE",
              "type": "FILE"
            }
          },
          {
            "id": 37030336,
            "mandatory": true,
            "formTag": {
              "id": 370636,
              "name": "Reconciliation acct",
              "type": "DROPDOWN"
            }
          },
          {
            "id": 37030337,
            "mandatory": true,
            "formTag": {
              "id": 370637,
              "name": "Currency",
              "type": "DROPDOWN"
            }
          },
          {
            "id": 37030338,
            "mandatory": true,
            "formTag": {
              "id": 370638,
              "name": "Is Vendor Your Customer?",
              "type": "DROPDOWN"
            }
          },
          {
            "id": 37030339,
            "mandatory": false,
            "formTag": {
              "id": 370639,
              "name": "Customer Code",
              "type": "TEXT"
            }
          },
          {
            "id": 37030340,
            "mandatory": false,
            "formTag": {
              "id": 370640,
              "name": "Service Tax File",
              "type": "FILE"
            }
          },
          {
            "id": 37030341,
            "mandatory": false,
            "formTag": {
              "id": 370641,
              "name": "Share with",
              "type": "TEXT"
            }
          },
          {
            "id": 37030342,
            "mandatory": false,
            "formTag": {
              "id": 370642,
              "name": "Additional File",
              "type": "FILE"
            }
          },
          {
            "id": 37030343,
            "mandatory": false,
            "formTag": {
              "id": 370643,
              "name": "Withholding Tax Details",
              "type": "PANEL"
            }
          },
          {
            "id": 37030344,
            "mandatory": false,
            "formTag": {
              "id": 370644,
              "name": "Company Code",
              "type": "TEXT"
            }
          },
          {
            "id": 37030345,
            "mandatory": true,
            "formTag": {
              "id": 370645,
              "name": "Withholding Tax Type",
              "type": "DROPDOWN"
            }
          },
          {
            "id": 37030346,
            "mandatory": true,
            "formTag": {
              "id": 370646,
              "name": "Subject to w/tax",
              "type": "CHECKBOX"
            }
          },
          {
            "id": 37030347,
            "mandatory": false,
            "formTag": {
              "id": 370647,
              "name": "Recipient Type",
              "type": "TEXT"
            }
          },
          {
            "id": 37030348,
            "mandatory": true,
            "formTag": {
              "id": 370648,
              "name": "Withholding Tax Code",
              "type": "DROPDOWN"
            }
          },
          {
            "id": 37030349,
            "mandatory": true,
            "formTag": {
              "id": 370649,
              "name": "All financial & bank details are verified",
              "type": "CHECKBOX"
            }
          },
          {
            "id": 37030350,
            "mandatory": false,
            "formTag": {
              "id": 370650,
              "name": "Field B",
              "type": "DATE"
            }
          }
        ]
      }
    ]
  }
}